{
  "last_run": "05:00 UTC (12:00 ICT, Mar 18)",
  "videos": {
    "XZXq5lP7xCk": {
      "title": "B\u1eacN T\u00c2M - L\u00c2M ANH | Ti\u1ebft m\u1ee5c Solo C\u00f4ng Di\u1ec5n 5 | T\u00c2N BINH TO\u00c0N N\u0102NG 2025",
      "views": 387712,
      "likes": 4515,
      "comments": 2676,
      "views_changed_at": "2026-03-18T05:00:17.974885",
      "views_day_start": 387361,
      "views_day_date": "2026-03-18",
      "likes_changed_at": "2026-03-18T02:37:20.986072",
      "likes_day_start": 4514,
      "likes_day_date": "2026-03-18",
      "comments_changed_at": "2026-03-14T21:31:38.890285",
      "comments_day_start": 2676,
      "comments_day_date": "2026-03-18"
    },
    "1Trlr6fWn-Y": {
      "title": "1% - PH\u00daC NGUY\u00caN // S\u00c2N KH\u1ea4U TINH HOA | T\u00c2N BINH TO\u00c0N N\u0102NG 2025",
      "views": 378246,
      "likes": 6653,
      "comments": 2388,
      "views_changed_at": "2026-03-18T05:00:17.974885",
      "views_day_start": 377940,
      "views_day_date": "2026-03-18",
      "likes_changed_at": "2026-03-17T19:08:01.044902",
      "likes_day_start": 6653,
      "likes_day_date": "2026-03-18",
      "comments_changed_at": "2026-03-17T19:08:01.044902",
      "comments_day_start": 2388,
      "comments_day_date": "2026-03-18"
    },
    "Iy_qH9EvuJY": {
      "title": "B\u1ea2NH T\u1eea TRONG CODE  - C\u01af\u1edcNG B\u1ea0CH | Ti\u1ebft m\u1ee5c Solo C\u00f4ng Di\u1ec5n 5 | T\u00c2N BINH TO\u00c0N N\u0102NG 2025",
      "views": 356049,
      "likes": 3630,
      "comments": 1934,
      "views_changed_at": "2026-03-18T05:00:17.974885",
      "views_day_start": 355923,
      "views_day_date": "2026-03-18",
      "likes_changed_at": "2026-03-18T05:00:17.974885",
      "likes_day_start": 3629,
      "likes_day_date": "2026-03-18",
      "comments_changed_at": "2026-03-18T05:00:17.974885",
      "comments_day_start": 1933,
      "comments_day_date": "2026-03-18"
    }
  }
}