{
  "last_run": "13:10 UTC (20:10 ICT, Mar 05)",
  "videos": {
    "XZXq5lP7xCk": {
      "title": "B\u1eacN T\u00c2M - L\u00c2M ANH | Ti\u1ebft m\u1ee5c Solo C\u00f4ng Di\u1ec5n 5 | T\u00c2N BINH TO\u00c0N N\u0102NG 2025",
      "views": 360740,
      "likes": 4418,
      "comments": 2675,
      "views_changed_at": "2026-03-05T13:10:36.675067",
      "views_day_start": 359451,
      "views_day_date": "2026-03-05",
      "likes_changed_at": "2026-03-05T13:10:36.675067",
      "likes_day_start": 4406,
      "likes_day_date": "2026-03-05",
      "comments_changed_at": "2026-03-04T15:50:00.298143",
      "comments_day_start": 2675,
      "comments_day_date": "2026-03-05"
    },
    "1Trlr6fWn-Y": {
      "title": "1% - PH\u00daC NGUY\u00caN // S\u00c2N KH\u1ea4U TINH HOA | T\u00c2N BINH TO\u00c0N N\u0102NG 2025",
      "views": 351709,
      "likes": 6483,
      "comments": 2328,
      "views_changed_at": "2026-03-05T13:10:36.675067",
      "views_day_start": 350569,
      "views_day_date": "2026-03-05",
      "likes_changed_at": "2026-03-05T13:10:36.675067",
      "likes_day_start": 6481,
      "likes_day_date": "2026-03-05",
      "comments_changed_at": "2026-03-05T13:10:36.675067",
      "comments_day_start": 2316,
      "comments_day_date": "2026-03-05"
    },
    "Iy_qH9EvuJY": {
      "title": "B\u1ea2NH T\u1eea TRONG CODE  - C\u01af\u1edcNG B\u1ea0CH | Ti\u1ebft m\u1ee5c Solo C\u00f4ng Di\u1ec5n 5 | T\u00c2N BINH TO\u00c0N N\u0102NG 2025",
      "views": 344199,
      "likes": 3545,
      "comments": 1919,
      "views_changed_at": "2026-03-05T13:10:36.675067",
      "views_day_start": 343536,
      "views_day_date": "2026-03-05",
      "likes_changed_at": "2026-03-05T13:10:36.675067",
      "likes_day_start": 3538,
      "likes_day_date": "2026-03-05",
      "comments_changed_at": "2026-03-04T10:07:35.878162",
      "comments_day_start": 1919,
      "comments_day_date": "2026-03-05"
    }
  }
}